{
    "homepage": "https://www.winitor.com",
    "description": "pestudio is used by Computer Emergency Response Teams and Labs worldwide in order to perform Malware Initial Assessment.",
    "version": "9.40",
    "license": "Shareware",
    "hash": "8F73CC4EE1EFE31551CFF3A27828A22A36DB055AFF0145A59BBF04335261D5EA",
    "url": "https://winitor.com/tools/pestudio/current/pestudio.zip",
    "extract_dir": "pestudio",
    "bin": "pestudio.exe",
    "shortcuts": [
        [
            "pestudio.exe",
            "PEStudio"
        ]
    ],
    "checkver": {
        "url": "https://www.winitor.com/tools/pestudio/changes.log",
        "re": "Version\\s(?<version>[\\d.]+)"
    },
    "autoupdate": {
        "url": "https://winitor.com/tools/pestudio/current/pestudio.zip"
    }
}
